{
    "kind": "SigNozCompositeQuery",
    "spec": {
        "queries": [
            {
                "type": "builder_query",
                "spec": {
                    "name": "A",
                    "signal": "metrics",
                    "expression": "A",
                    "aggregations": [
                        {
                            "metricName": "redis_keyspace_hits",
                            "timeAggregation": "rate",
                            "spaceAggregation": "sum",
                            "reduceTo": "sum"
                        }
                    ],
                    "filter": {
                        "expression": "host_name IN $host_name"
                    }
                }
            },
            {
                "type": "builder_query",
                "spec": {
                    "name": "B",
                    "signal": "metrics",
                    "expression": "B",
                    "aggregations": [
                        {
                            "metricName": "redis_keyspace_misses",
                            "timeAggregation": "rate",
                            "spaceAggregation": "sum",
                            "reduceTo": "sum"
                        }
                    ],
                    "filter": {
                        "expression": "host_name IN $host_name"
                    }
                }
            },
            {
                "type": "builder_formula",
                "spec": {
                    "name": "F1",
                    "expression": "A / (A + B) * 100",
                    "legend": "Hit rate %"
                }
            }
        ]
    }
}
